algolib/__init__.py
cutelib-0.0.1.dist-info/License
cutelib-0.0.1.dist-info/METADATA
cutelib-0.0.1.dist-info/WHEEL
cutelib-0.0.1.dist-info/top_level.txt
cutelib-0.0.1.dist-info/RECORD
