Metadata-Version: 2.1
Name: cutelib
Version: 0.0.1
Summary: A algorithm library.
Author-email: xk2013 <hzk201312@163.com>
Project-URL: Homepage, https://github.com/xk2013/cutelib
Project-URL: Issues, https://github.com/xk2013/cutelib/issues
Classifier: Programming Language :: Python :: 3
Classifier: License :: OSI Approved :: GNU Lesser General Public License v3 or later (LGPLv3+)
Classifier: Operating System :: OS Independent
Requires-Python: >=3.8
License-File: License
